solar_utils/NREL_DISCLAIMERS-COPYRIGHTS-LICENSES.txt
solar_utils/__init__.py
solar_utils/core.py
solar_utils/dummy.cp36-win_amd64.pyd
solar_utils/exceptions.py
solar_utils/solposAM.dll
solar_utils/spectrl2.dll
solar_utils/tests/__init__.py
solar_utils/tests/test_cdlls.py
solar_utils/tests/test_spectrl2_data.json
SolarUtils-0.3.dist-info/LICENSE
SolarUtils-0.3.dist-info/METADATA
SolarUtils-0.3.dist-info/WHEEL
SolarUtils-0.3.dist-info/top_level.txt
SolarUtils-0.3.dist-info/RECORD
