Metadata-Version: 2.1
Name: SolarUtils
Version: 0.3
Summary: Python wrappers around NREL SOLPOS and SPECTRL2
Home-page: https://github.com/SunPower/SolarUtils
Author: Mark Mikofski
Author-email: mark.mikofski@sunpowercorp.com
License: BSD 3-Clause
Platform: win32
Platform: linux
Platform: linux2
Platform: darwin
Provides-Extra: testing
Requires-Dist: numpy ; extra == 'testing'
Requires-Dist: nose ; extra == 'testing'
